usefulib/__init__.py
usefulib/_usefulibs.py
usefulib/tests.py
usefulib/temp_data/__init__.py
usefulib-1.0.5.dist-info/LICENSE
usefulib-1.0.5.dist-info/METADATA
usefulib-1.0.5.dist-info/WHEEL
usefulib-1.0.5.dist-info/top_level.txt
usefulib-1.0.5.dist-info/RECORD
