Metadata-Version: 2.1
Name: usefulib
Version: 1.0.5
Summary: A collection of assorted methods to make small tasks easier.
Home-page: UNKNOWN
Author: Hamd Waseem
Author-email: <codingboy.cw@gmail.com>
License: UNKNOWN
Keywords: python,useful,usefulib,collection
Platform: UNKNOWN
Classifier: Development Status :: 5 - Production/Stable
Classifier: Intended Audience :: Developers
Classifier: Programming Language :: Python :: 3
Classifier: Operating System :: Unix
Classifier: Operating System :: MacOS :: MacOS X
Classifier: Operating System :: Microsoft :: Windows
License-File: LICENSE
Requires-Dist: numpy
